mysql_ch_replicator/.gitignore
mysql_ch_replicator/__init__.py
mysql_ch_replicator/binlog_replicator.py
mysql_ch_replicator/clickhouse_api.py
mysql_ch_replicator/common.py
mysql_ch_replicator/config.py
mysql_ch_replicator/converter.py
mysql_ch_replicator/db_optimizer.py
mysql_ch_replicator/db_replicator.py
mysql_ch_replicator/db_replicator_initial.py
mysql_ch_replicator/db_replicator_realtime.py
mysql_ch_replicator/enum/__init__.py
mysql_ch_replicator/enum/converter.py
mysql_ch_replicator/enum/ddl_parser.py
mysql_ch_replicator/enum/parser.py
mysql_ch_replicator/enum/utils.py
mysql_ch_replicator/main.py
mysql_ch_replicator/monitoring.py
mysql_ch_replicator/mysql_api.py
mysql_ch_replicator/pymysqlreplication/__init__.py
mysql_ch_replicator/pymysqlreplication/binlogstream.py
mysql_ch_replicator/pymysqlreplication/bitmap.py
mysql_ch_replicator/pymysqlreplication/column.py
mysql_ch_replicator/pymysqlreplication/constants/BINLOG.py
mysql_ch_replicator/pymysqlreplication/constants/CHARSET.py
mysql_ch_replicator/pymysqlreplication/constants/FIELD_TYPE.py
mysql_ch_replicator/pymysqlreplication/constants/NONE_SOURCE.py
mysql_ch_replicator/pymysqlreplication/constants/STATUS_VAR_KEY.py
mysql_ch_replicator/pymysqlreplication/constants/__init__.py
mysql_ch_replicator/pymysqlreplication/cpp_accelerated.py
mysql_ch_replicator/pymysqlreplication/event.py
mysql_ch_replicator/pymysqlreplication/exceptions.py
mysql_ch_replicator/pymysqlreplication/gtid.py
mysql_ch_replicator/pymysqlreplication/json_binary.py
mysql_ch_replicator/pymysqlreplication/libmysqljsonparse.dylib
mysql_ch_replicator/pymysqlreplication/libmysqljsonparse.so
mysql_ch_replicator/pymysqlreplication/libmysqljsonparse_x86_64.so
mysql_ch_replicator/pymysqlreplication/packet.py
mysql_ch_replicator/pymysqlreplication/row_event.py
mysql_ch_replicator/pymysqlreplication/table.py
mysql_ch_replicator/pymysqlreplication/tests/__init__.py
mysql_ch_replicator/pymysqlreplication/tests/base.py
mysql_ch_replicator-0.1.9.dist-info/METADATA
mysql_ch_replicator-0.1.9.dist-info/WHEEL
mysql_ch_replicator-0.1.9.dist-info/entry_points.txt
mysql_ch_replicator-0.1.9.dist-info/licenses/LICENSE
mysql_ch_replicator-0.1.9.dist-info/RECORD
