Metadata-Version: 2.4
Name: mysql-ch-replicator
Version: 0.1.9
Summary: Tool for replication of MySQL databases to ClickHouse
License: MIT
License-File: LICENSE
Author: Filipp Ozinov
Author-email: filipp@bakanov.su
Requires-Python: >=3.9,<4.0
Classifier: License :: OSI Approved :: MIT License
Classifier: Programming Language :: Python :: 3
Classifier: Programming Language :: Python :: 3.9
Classifier: Programming Language :: Python :: 3.10
Classifier: Programming Language :: Python :: 3.11
Classifier: Programming Language :: Python :: 3.12
Classifier: Programming Language :: Python :: 3.13
Classifier: Programming Language :: Python :: 3.14
Requires-Dist: clickhouse-connect (>=0.7.8)
Requires-Dist: fastapi (>=0.115.6,<0.116.0)
Requires-Dist: mysql-connector-python (>=8.3.0)
Requires-Dist: packaging (>=21.3)
Requires-Dist: pymysql (>=1.0.0)
Requires-Dist: pyparsing (>=3.0.8)
Requires-Dist: pyyaml (>=5.0.1)
Requires-Dist: requests (>=2.32.3,<3.0.0)
Requires-Dist: sqlparse (>=0.5.1)
Requires-Dist: uvicorn (>=0.34.0,<0.35.0)
